jinja2_simple_tags.py
jinja2_simple_tags-0.6.1.dist-info/LICENSE
jinja2_simple_tags-0.6.1.dist-info/METADATA
jinja2_simple_tags-0.6.1.dist-info/WHEEL
jinja2_simple_tags-0.6.1.dist-info/top_level.txt
jinja2_simple_tags-0.6.1.dist-info/RECORD
